cropimage/__init__.py
cropimage/constants.py
cropimage/cropper.py
cropimage/haarcascade_frontalface_default.xml
cropimage/haarcascade_profileface.xml
cropimage_dh-0.0.7.dist-info/LICENSE
cropimage_dh-0.0.7.dist-info/METADATA
cropimage_dh-0.0.7.dist-info/WHEEL
cropimage_dh-0.0.7.dist-info/top_level.txt
cropimage_dh-0.0.7.dist-info/RECORD
