Metadata-Version: 2.1
Name: cropimage-dh
Version: 0.0.7
Summary: A simple toolkit for detecting and cropping main body from pictures.
Home-page: https://github.com/haofanwang/cropimage
Author: D8ahazard
Author-email: donate.to.digtalhigh@gmail.com
Classifier: Programming Language :: Python :: 3
Classifier: License :: OSI Approved :: Apache Software License
Classifier: Operating System :: OS Independent
License-File: LICENSE
